SF3/__init__.py
SF3/crypto.py
sf3-0.1.0.dist-info/METADATA
sf3-0.1.0.dist-info/WHEEL
sf3-0.1.0.dist-info/top_level.txt
sf3-0.1.0.dist-info/RECORD
