Metadata-Version: 2.1
Name: sf3
Version: 0.1.0
Summary: Secure File Encryption and Execution Tool
Author: CODESF3
Classifier: Programming Language :: Python :: 3
Classifier: License :: OSI Approved :: MIT License
Classifier: Operating System :: OS Independent
Requires-Python: >=3.6
